[
  {
    "officeName": "Ghoghla S.O",
    "pincode": "362540",
    "officeType": "S.O",
    "deliveryStatus": "Delivery",
    "divisionName": "Junagadh",
    "regionName": "Rajkot",
    "circleName": "Gujarat",
    "taluk": "Diu U.T.",
    "districtName": "Diu",
    "stateName": "DAMAN & DIU    "
  },
  {
    "officeName": "Diu S.O",
    "pincode": "362520",
    "officeType": "S.O",
    "deliveryStatus": "Delivery",
    "divisionName": "Junagadh",
    "regionName": "Rajkot",
    "circleName": "Gujarat",
    "taluk": "Diu",
    "districtName": "Diu",
    "stateName": "DAMAN & DIU  "
  },
  {
    "officeName": "Diu Zampa S.O",
    "pincode": "362520",
    "officeType": "S.O",
    "deliveryStatus": "Non-Delivery",
    "divisionName": "Junagadh",
    "regionName": "Rajkot",
    "circleName": "Gujarat",
    "taluk": "Diu",
    "districtName": "Diu",
    "stateName": "DAMAN & DIU   "
  },
  {
    "officeName": "Wanakbara S.O",
    "pincode": "362570",
    "officeType": "S.O",
    "deliveryStatus": "Delivery",
    "divisionName": "Junagadh",
    "regionName": "Rajkot",
    "circleName": "Gujarat",
    "taluk": "NA",
    "districtName": "Diu",
    "stateName": "DAMAN & DIU "
  },
  {
    "officeName": "Fudam B.O",
    "pincode": "362520",
    "officeType": "B.O",
    "deliveryStatus": "Delivery",
    "divisionName": "Junagadh",
    "regionName": "Rajkot",
    "circleName": "Gujarat",
    "taluk": "Diu",
    "districtName": "Diu",
    "stateName": "DAMAN & DIU"
  },
  {
    "officeName": "Bucharvada B.O",
    "pincode": "362570",
    "officeType": "B.O",
    "deliveryStatus": "Delivery",
    "divisionName": "Junagadh",
    "regionName": "Rajkot",
    "circleName": "Gujarat",
    "taluk": "Diu",
    "districtName": "Diu",
    "stateName": "DAMAN & DIU      "
  },
  {
    "officeName": "Daman I.E. S.O",
    "pincode": "396215",
    "officeType": "S.O",
    "deliveryStatus": "Delivery",
    "divisionName": "Valsad",
    "regionName": "Vadodara",
    "circleName": "Gujarat",
    "taluk": "Daman",
    "districtName": "Daman",
    "stateName": "DAMAN & DIU  "
  },
  {
    "officeName": "Moti Daman S.O",
    "pincode": "396220",
    "officeType": "S.O",
    "deliveryStatus": "Delivery",
    "divisionName": "Valsad",
    "regionName": "Vadodara",
    "circleName": "Gujarat",
    "taluk": "Daman",
    "districtName": "Daman",
    "stateName": "DAMAN & DIU  "
  },
  {
    "officeName": "Marvad B.O",
    "pincode": "396210",
    "officeType": "B.O",
    "deliveryStatus": "Delivery",
    "divisionName": "Valsad",
    "regionName": "Vadodara",
    "circleName": "Gujarat",
    "taluk": "Daman",
    "districtName": "Daman",
    "stateName": "DAMAN & DIU      "
  },
  {
    "officeName": "Dunetha B.O",
    "pincode": "396210",
    "officeType": "B.O",
    "deliveryStatus": "Delivery",
    "divisionName": "Valsad",
    "regionName": "Vadodara",
    "circleName": "Gujarat",
    "taluk": "Daman",
    "districtName": "Daman",
    "stateName": "DAMAN & DIU     "
  },
  {
    "officeName": "Kachigam B.O",
    "pincode": "396215",
    "officeType": "B.O",
    "deliveryStatus": "Delivery",
    "divisionName": "Valsad",
    "regionName": "Vadodara",
    "circleName": "Gujarat",
    "taluk": "Daman",
    "districtName": "Daman",
    "stateName": "DAMAN & DIU    "
  },
  {
    "officeName": "Magarwada B.O",
    "pincode": "396220",
    "officeType": "B.O",
    "deliveryStatus": "Delivery",
    "divisionName": "Valsad",
    "regionName": "Vadodara",
    "circleName": "Gujarat",
    "taluk": "Daman",
    "districtName": "Daman",
    "stateName": "DAMAN & DIU   "
  },
  {
    "officeName": "Nani Vankad B.O",
    "pincode": "396210",
    "officeType": "B.O",
    "deliveryStatus": "Delivery",
    "divisionName": "Valsad",
    "regionName": "Vadodara",
    "circleName": "Gujarat",
    "taluk": "Daman",
    "districtName": "Daman",
    "stateName": "DAMAN & DIU "
  },
  {
    "officeName": "Dabhel B.O",
    "pincode": "396215",
    "officeType": "B.O",
    "deliveryStatus": "Delivery",
    "divisionName": "Valsad",
    "regionName": "Vadodara",
    "circleName": "Gujarat",
    "taluk": "Daman",
    "districtName": "Daman",
    "stateName": "DAMAN & DIU      "
  },
  {
    "officeName": "Dholar B.O",
    "pincode": "396220",
    "officeType": "B.O",
    "deliveryStatus": "Delivery",
    "divisionName": "Valsad",
    "regionName": "Vadodara",
    "circleName": "Gujarat",
    "taluk": "Daman",
    "districtName": "Daman",
    "stateName": "DAMAN & DIU      "
  },
  {
    "officeName": "Varkund B.O",
    "pincode": "396210",
    "officeType": "B.O",
    "deliveryStatus": "Delivery",
    "divisionName": "Valsad",
    "regionName": "Vadodara",
    "circleName": "Gujarat",
    "taluk": "Daman",
    "districtName": "Daman",
    "stateName": "DAMAN & DIU     "
  },
  {
    "officeName": "Daman S.O",
    "pincode": "396210",
    "officeType": "S.O",
    "deliveryStatus": "Delivery",
    "divisionName": "Valsad",
    "regionName": "Vadodara",
    "circleName": "Gujarat",
    "taluk": "Daman",
    "districtName": "Daman",
    "stateName": "DAMAN & DIU"
  },
  {
    "officeName": "Kadaiya B.O",
    "pincode": "396210",
    "officeType": "B.O",
    "deliveryStatus": "Delivery",
    "divisionName": "Valsad",
    "regionName": "Vadodara",
    "circleName": "Gujarat",
    "taluk": "Daman",
    "districtName": "Daman",
    "stateName": "DAMAN & DIU     "
  },
  {
    "officeName": "Kunta B.O",
    "pincode": "396215",
    "officeType": "B.O",
    "deliveryStatus": "Delivery",
    "divisionName": "Valsad",
    "regionName": "Vadodara",
    "circleName": "Gujarat",
    "taluk": "Daman",
    "districtName": "Daman",
    "stateName": "DAMAN & DIU"
  },
  {
    "officeName": "Bhimpore B.O",
    "pincode": "396210",
    "officeType": "B.O",
    "deliveryStatus": "Delivery",
    "divisionName": "Valsad",
    "regionName": "Vadodara",
    "circleName": "Gujarat",
    "taluk": "Daman",
    "districtName": "Daman",
    "stateName": "DAMAN & DIU    "
  }
]